{
  "id": "25408058",
  "nom": "Arrangement par défaut",
  "clef_originale": null,
  "tempo": null,
  "chord_chart": "[Bb]  Tu es celui qui ouvre les [F]yeux des aveugles\r\n[C]  Tu es celui qui change les [Gm]vies\r\n[Bb]  Tu prononces une parole et ce [F]qui était mort reprend [C]vie, [Gm]Jésus\r\n\r\n[Bb  ]Tu es celui qui a ins[F]piré cette œuvre\r\n[C]  Qui la mènera jusqu'au [Gm]bout\r\n[Bb]  Tu avais décidé d'é[F]crire cette histoire avec[C] nou[Gm]s\r\n\r\n\r\n[Bb]  Maintenant Seigneur, souffle sur nos [F]pays, envahis nos vill[C]ages, viens toucher nos fami[Gm]lles\r\n[Bb]  Maintenant Seigneur, fais connaître le [F]nom, qui peut guérir les nat[C]ions, le nom de Jésus [Gm]Christ\r\n\r\n\r\n\r\n[Bb]  Les défis sont grands, nous [F]en avons conscience\r\n[C]  Tu les connais mieux que [Gm]nous, Jésus\r\n[Bb]  Mais nous voulons croire que [F]rien n'est impossible\r\n[C]   Saint Esprit nous deman[Gm]dons que maintenant\r\n\r\nFais tomber la pluie d'en haut\r\nFais tomber la pluie du ciel"
}